fmu/__init__.py
fmu/settings/__init__.py
fmu/settings/_fmu_dir.py
fmu/settings/_global_config.py
fmu/settings/_init.py
fmu/settings/_logging.py
fmu/settings/_readme_texts.py
fmu/settings/_version.py
fmu/settings/py.typed
fmu/settings/types.py
fmu/settings/_resources/__init__.py
fmu/settings/_resources/cache_manager.py
fmu/settings/_resources/changelog_manager.py
fmu/settings/_resources/config_managers.py
fmu/settings/_resources/lock_manager.py
fmu/settings/_resources/log_manager.py
fmu/settings/_resources/mappings_manager.py
fmu/settings/_resources/pydantic_resource_manager.py
fmu/settings/_resources/user_session_log_manager.py
fmu/settings/models/__init__.py
fmu/settings/models/_enums.py
fmu/settings/models/change_info.py
fmu/settings/models/event_info.py
fmu/settings/models/lock_info.py
fmu/settings/models/log.py
fmu/settings/models/mappings.py
fmu/settings/models/project_config.py
fmu/settings/models/user_config.py
fmu_settings-0.15.0.dist-info/licenses/LICENSE
fmu_settings-0.15.0.dist-info/METADATA
fmu_settings-0.15.0.dist-info/WHEEL
fmu_settings-0.15.0.dist-info/top_level.txt
fmu_settings-0.15.0.dist-info/RECORD
