Metadata-Version: 2.4
Name: fmu-settings
Version: 0.15.0
Summary: A library for managing FMU settings
Author-email: Equinor <fg-fmu_atlas@equinor.com>
License: GPL-3.0
Project-URL: Homepage, https://github.com/equinor/fmu-settings
Project-URL: Repository, https://github.com/equinor/fmu-settings
Project-URL: Documentation, https://github.com/equinor/fmu-settings
Classifier: Development Status :: 3 - Alpha
Classifier: Topic :: Scientific/Engineering
Classifier: Topic :: Utilities
Classifier: Operating System :: POSIX :: Linux
Classifier: Programming Language :: Python :: 3.11
Classifier: Programming Language :: Python :: 3.12
Classifier: Programming Language :: Python :: 3.13
Classifier: Natural Language :: English
Requires-Python: >=3.11
License-File: LICENSE
Requires-Dist: PyYAML
Requires-Dist: annotated_types
Requires-Dist: fmu-config
Requires-Dist: fmu-datamodels
Requires-Dist: pandas
Requires-Dist: pydantic
Provides-Extra: dev
Requires-Dist: mypy; extra == "dev"
Requires-Dist: pandas-stubs; extra == "dev"
Requires-Dist: pytest; extra == "dev"
Requires-Dist: pytest-cov; extra == "dev"
Requires-Dist: pytest-mock; extra == "dev"
Requires-Dist: pytest-xdist; extra == "dev"
Requires-Dist: ruff; extra == "dev"
Requires-Dist: types-PyYAML; extra == "dev"
Dynamic: license-file
